configvlm/ConfigVLM.py
configvlm/__init__.py
configvlm/extra/BEN_DataModule_LMDB_Encoder.py
configvlm/extra/BEN_lmdb_utils.py
configvlm/extra/COCOQA_DataModule.py
configvlm/extra/CustomTorchClasses.py
configvlm/extra/RSVQAxBEN_DataModule_LMDB_Encoder.py
configvlm/extra/__init__.py
configvlm/extra/mock_data/.coverage
configvlm/extra/mock_data/BigEarthNetEncoded.lmdb/data.mdb
configvlm/extra/mock_data/BigEarthNetEncoded.lmdb/lock.mdb
configvlm/extra/mock_data/COCO-QA_QA_test.json
configvlm/extra/mock_data/COCO-QA_QA_train.json
configvlm/extra/mock_data/VQA_RSVQAxBEN/RSVQAxBEN_QA_test.json
configvlm/extra/mock_data/VQA_RSVQAxBEN/RSVQAxBEN_QA_test_subset.json
configvlm/extra/mock_data/VQA_RSVQAxBEN/RSVQAxBEN_QA_train.json
configvlm/extra/mock_data/VQA_RSVQAxBEN/RSVQAxBEN_QA_train_subset.json
configvlm/extra/mock_data/VQA_RSVQAxBEN/RSVQAxBEN_QA_val.json
configvlm/extra/mock_data/VQA_RSVQAxBEN/RSVQAxBEN_QA_val_subset.json
configvlm/extra/mock_data/gen_mock_data_BEN.py
configvlm/extra/mock_data/gen_mock_data_COCOQA.py
configvlm/extra/mock_data/images/COCO_train2014_000000001822.jpg
configvlm/extra/mock_data/images/COCO_train2014_000000024221.jpg
configvlm/extra/mock_data/images/COCO_train2014_000000109182.jpg
configvlm/extra/mock_data/images/COCO_train2014_000000121792.jpg
configvlm/extra/mock_data/images/COCO_train2014_000000132699.jpg
configvlm/extra/mock_data/images/COCO_train2014_000000166560.jpg
configvlm/extra/mock_data/images/COCO_train2014_000000168874.jpg
configvlm/extra/mock_data/images/COCO_train2014_000000170588.jpg
configvlm/extra/mock_data/images/COCO_train2014_000000209531.jpg
configvlm/extra/mock_data/images/COCO_train2014_000000241821.jpg
configvlm/extra/mock_data/images/COCO_train2014_000000300741.jpg
configvlm/extra/mock_data/images/COCO_train2014_000000318491.jpg
configvlm/extra/mock_data/images/COCO_train2014_000000365587.jpg
configvlm/extra/mock_data/images/COCO_train2014_000000377703.jpg
configvlm-0.1.1.dist-info/LICENSE
configvlm-0.1.1.dist-info/METADATA
configvlm-0.1.1.dist-info/WHEEL
configvlm-0.1.1.dist-info/RECORD
