Metadata-Version: 2.1
Name: configvlm
Version: 0.1.1
Summary: A state-of-the-art tool for Python developers seeking to rapidly and iteratively develop vision and language models within the [`pytorch`](https://pytorch.org/) framework
Author: Leonard Hackel
Author-email: l.hackel@tu-berlin.de
Requires-Python: >=3.10,<4.0
Classifier: Programming Language :: Python :: 3
Classifier: Programming Language :: Python :: 3.10
Classifier: Programming Language :: Python :: 3.11
Requires-Dist: appdirs (>=1.4.4,<2.0.0)
Requires-Dist: bigearthnet-encoder (>=0.3.0,<0.4.0)
Requires-Dist: fvcore (>=0.1.5.post20221221,<0.2.0)
Requires-Dist: lightning-bolts (>=0.6.0.post1,<0.7.0)
Requires-Dist: lmdb (>=1.4.0,<2.0.0)
Requires-Dist: matplotlib (>=3.6.3,<4.0.0)
Requires-Dist: numpy (>=1.24.1,<2.0.0)
Requires-Dist: pytorch-lightning (>=1.9.0,<2.0.0)
Requires-Dist: scikit-learn (>=1.2.1,<2.0.0)
Requires-Dist: timm (>=0.6.12,<0.7.0)
Requires-Dist: torch (>=1.13.1)
Requires-Dist: transformers (>=4.26.0,<5.0.0)
